pytorch_lamb/__init__.py
pytorch_lamb/lamb.py
pytorch_lamb-1.0.0.dist-info/LICENSE
pytorch_lamb-1.0.0.dist-info/METADATA
pytorch_lamb-1.0.0.dist-info/WHEEL
pytorch_lamb-1.0.0.dist-info/top_level.txt
pytorch_lamb-1.0.0.dist-info/RECORD
