Metadata-Version: 2.1
Name: pytorch-lamb
Version: 1.0.0
Summary: UNKNOWN
Home-page: https://github.com/cybertronai/pytorch-lamb
Author: Ben Mann
Author-email: me@benjmann.net
License: MIT
Platform: UNKNOWN
Requires-Dist: torch (>=0.4.1)
Requires-Dist: tqdm
Requires-Dist: tensorboardX
Requires-Dist: torchvision
